Workbook

Sheet FA
C2: عنوان پروژه | D2: پروژه 400 هزارتنی کاتد مکران
C3: عنوان فرعی پروژه | D3: کارخانه ذوب و اسید فسفریک چابهار
U4: دوره | V4: تولید فسفریک | W4: هزینه عملیاتی | X4: هزینه سرمایه گذاری | Y4: درآمد عملیاتی | Z4: جریان های نقدی بعد از مالیات (یورو) | AB4: جریان نقدی خالص پس از کسر مالیات | AC4: جریان نقد آزاد | AD4: هزینه های عملیاتی | AE4: درآمدهای عملیاتی | AF4: هزینه های سرمایه‌گذاری | AG4: دوره
C5: خلاصه پروژه | V5: (تن) | W5: (یورو) | X5: (یورو) | Y5: (یورو) | AB5: -746033277 | AC5: -746033277 | AD5: 0 | AE5: 0 | AF5: 746033277 | AG5: 0
C6: صنعت | D6: مس و فلزات غیر آهنی | U6: 0 | V6: 0 | W6: 0 | X6: 610250945 | Y6: 0 | Z6: -610167520 | AB6: -447619966 | AC6: -447619966 | AD6: 0 | AE6: 0 | AF6: 447619966 | AG6: 1
C7: زیرصنعت | D7: زنجیره پایین دست صنعت مس | U7: 1 | V7: 726700 | W7: 566826000 | Y7: 799370000 | Z7: 232544000 | AB7: -298413311 | AC7: -298413311 | AD7: 0 | AE7: 0 | AF7: 298413311 | AG7: 2
C8: مکان | D8: منطقه آزاد چابهار | U8: 2 | V8: 894400 | W8: 697632000 | Y8: 983840000 | Z8: 286208000 | AB8: 139072884 | AC8: 139072884 | AD8: 2410227116 | AE8: 2549300000 | AF8: 0 | AG8: 3
C9: درصد پیشرفت پروژه | D9: 0 | U9: 3 | V9: 1118000 | W9: 872040000 | Y9: 1229800000 | Z9: 357760000 | AB9: 171166626 | AC9: 171166626 | AD9: 2966433374 | AE9: 3137600000 | AF9: 0 | AG9: 4
C10: شرح پروژه | D10: تعریف طرح با هدف نیل به تولید سالیانه 1,000,000 تن کاتد مس و 570,000 تن اسید فسفریک در منطقه آزاد چابهار | U10: 4 | V10: 1118000 | W10: 872040000 | Y10: 1229800000 | Z10: 357760000 | AB10: 192562455 | AC10: 192562455 | AD10: 3337237545 | AE10: 3529800000 | AF10: 0 | AG10: 5
C11: وضعیت اجرای پروژه | D11: متوقف | U11: 5 | V11: 1118000 | W11: 872040000 | Y11: 1229800000 | Z11: 357760000 | AB11: 213958283 | AC11: 213958283 | AD11: 3708041717 | AE11: 3922000000 | AF11: 0 | AG11: 6
C12: وضعیت تامین مالی | D12: اقدامی انجام نشده است | U12: 6 | V12: 1118000 | W12: 872040000 | Y12: 1229800000 | Z12: 357760000 | AB12: 213958283 | AC12: 213958283 | AD12: 3708041717 | AE12: 3922000000 | AF12: 0 | AG12: 7
C13: ریسک های اصلی | D13: محدودیت تامین مالی و ماده اولیه | U13: 7 | V13: 1118000 | W13: 872040000 | Y13: 1229800000 | Z13: 357760000 | AB13: 213958283 | AC13: 213958283 | AD13: 3708041717 | AE13: 3922000000 | AF13: 0 | AG13: 8
U14: 8 | V14: 1118000 | W14: 872040000 | Y14: 1229800000 | Z14: 357760000 | AB14: 213958283 | AC14: 213958283 | AD14: 3708041717 | AE14: 3922000000 | AF14: 0 | AG14: 9
C15: هزینه های سرمایه گذاری | U15: 9 | V15: 1118000 | W15: 872040000 | Y15: 1229800000 | Z15: 357760000 | AB15: 213958283 | AC15: 213958283 | AD15: 3708041717 | AE15: 3922000000 | AF15: 0 | AG15: 10
C16: عنوان | D16: مبلغ (میلیون یورو) | U16: 10 | V16: 1118000 | W16: 872040000 | Y16: 1229800000 | Z16: 357760000 | AB16: 213958283 | AC16: 213958283 | AD16: 3708041717 | AE16: 3922000000 | AF16: 0 | AG16: 11
C17: مجموع سرمایه گذاری | D17: 2050 | U17: 11 | V17: 1118000 | W17: 872040000 | Y17: 1229800000 | Z17: 357760000 | AB17: 213958283 | AC17: 213958283 | AD17: 3708041717 | AE17: 3922000000 | AF17: 0 | AG17: 12
C18: مهندسی و دانش فنی | D18: 164 | U18: 12 | V18: 1118000 | W18: 872040000 | Y18: 1229800000 | Z18: 357760000 | AB18: 213958283 | AC18: 213958283 | AD18: 3708041717 | AE18: 3922000000 | AF18: 0 | AG18: 13
C19: ماشین آلات و تجهیزات | D19: 1435 | U19: 13 | V19: 1118000 | W19: 872040000 | Y19: 1229800000 | Z19: 357760000 | AB19: 213958283 | AC19: 213958283 | AD19: 3708041717 | AE19: 3922000000 | AF19: 0 | AG19: 14
C20: ساخت و راه اندازی | D20: 142 | U20: 14 | V20: 1118000 | W20: 872040000 | Y20: 1229800000 | Z20: 357760000 | AB20: 213958283 | AC20: 213958283 | AD20: 3708041717 | AE20: 3922000000 | AF20: 0 | AG20: 15
C21: یوتیلیتی (هزینه ایجاد تاسیسات زیرساختی پشتیبانی تولید) | D21: 155 | U21: 15 | V21: 1118000 | W21: 872040000 | Y21: 1229800000 | Z21: 357760000 | AB21: 213958283 | AC21: 213958283 | AD21: 3708041717 | AE21: 3922000000 | AF21: 0 | AG21: 16
C22: هزینه های پیش از راه اندازی | D22: 100 | U22: 16 | V22: 1118000 | W22: 872040000 | Y22: 1229800000 | Z22: 357760000 | AB22: 213958283 | AC22: 213958283 | AD22: 3708041717 | AE22: 3922000000 | AF22: 0 | AG22: 17
C23: هزینه های پیش بینی نشده | D23: 105 | U23: 17 | V23: 1118000 | W23: 872040000 | Y23: 1229800000 | Z23: 357760000 | AB23: 213958283 | AC23: 213958283 | AD23: 3708041717 | AE23: 3922000000 | AF23: 0 | AG23: 18
C24: سرمایه در گردش | D24: 49 | U24: 18 | V24: 1118000 | W24: 872040000 | Y24: 1229800000 | Z24: 357760000 | AB24: 213958283 | AC24: 213958283 | AD24: 3708041717 | AE24: 3922000000 | AF24: 0 | AG24: 19
U25: 19 | V25: 1118000 | W25: 872040000 | Y25: 1229800000 | Z25: 357760000 | AB25: 213958283 | AC25: 213958283 | AD25: 3708041717 | AE25: 3922000000 | AF25: 0 | AG25: 20
C26: تحلیل سرمایه گذاری | U26: 20 | V26: 1118000 | W26: 872040000 | Y26: 1229800000 | Z26: 357760000 | AB26: 213958283 | AC26: 213958283 | AD26: 3708041717 | AE26: 3922000000 | AF26: 0 | AG26: 21
C27: عنوان | D27: % | AB27: 213958283 | AC27: 213958283 | AD27: 3708041717 | AE27: 3922000000 | AF27: 0 | AG27: 22
C28: درصد ارزی کل سرمایه گذاری | D28: 1
C29: دوره ساخت (سال) | D29: 3
C30: دوره بازگشت سرمایه (سال) | D30: 20 | V30: کل (یورو) | W30: هزینه ریالی (میلیون ریال) | X30: هزینه ارزی ( یورو) | Y30: اقلام هزینه های عملیاتی | AB30: ردیف | AC30: شرح | AD30: یورو در سال
C31: درآمد عملیاتی سالانه (EBIT) | D31: 735.96 | V31: 622782692 | W31: 26655010 | X31: 579069217 | Y31: مواد اولیه و مصرفی | AB31: 1 | AC31: کنسانتره | AD31: 3253663214
C32: درآمد خالص سالانه | D32: 551.97 | V32: 35853214 | W32: 15775414 | X32: 0 | Y32: یوتیلیتی و تاسیسات مصرفی | AB32: 2 | AC32: مواد مصرفی | AD32: 29874220
C33: نرخ بازده داخلی (IRR) | D33: 0.2303 | V33: 64288522 | W33: 28286950 | X33: 0 | Y33: تعمیر و نگهداری | AB33: 3 | AC33: زغالسنگ | AD33: 17042
C34: خالص ارزش فعلی پروژه با نرخ تنزیل 12% (NPV) | D34: 2,067 میلیون یورو | V34: 9890542 | W34: 4351838 | X34: 0 | Y34: نیروی انسانی | AB34: 4 | AC34: گاز طبیعی | AD34: 818730
V35: 98658155 | W35: 14687455 | X35: 67235903 | Y35: هزینه سربار | AB35: 5 | AC35: برق | AD35: 8273828
C36: جزئیات درآمدی | V36: 12363177 | W36: 5439798 | X36: 0 | Y36: هزینه بازاریابی و فروش | AB36: 6 | AC36: آب | AD36: 314014
C37: نام محصول | D37: ظرفیت تولید سالانه | V37: 15948499 | W37: 1631939 | X37: 12606732 | Y37: قطعات یدکی | AB37: 7 | AC37: نیروی کار مستقیم | AD37: 36743494
C38: کاتد مس | D38: 400,000 تن در سال | V38: 11225765 | W38: 3263879 | X38: 3922094 | Y38: هزینه های پیش بینی نشده | AB38: 8 | AC38: نگهداری (5 درصد) | AD38: 28677205
C39: اسید سولفوریک | D39: 1,720,000 تن در سال | V39: 871010565 | W39: 100092283 | X39: 662833947 | Y39: کل | AB39: 9 | AC39: هزینه های پیشبینی نشده | AD39: 9991544
C40: اسید فسفریک | D40: 570,000 تن در سال (P2O5 100%) | AB40: مجموع | AD40: 3368526666
C41: لجن آندی | D41: 1,200 تن در سال
C42: درآمد سالانه (میانگین 25 ساله) | D42: 5,150 میلیون یورو | AB42: ردیف | AC42: شرح | AD42: یورو در سال
C43: درصد درآمد ارزی | D43: 1 | AB43: 1 | AC43: مواد مصرفی | AD43: 277017
C44: بازار هدف | D44: صادرات | AB44: 2 | AC44: برق | AD44: 6619654
C45: تفکیک درآمد محصولات
C46: محصول | E46: تولید سالانه (تن) | F46: درآمد سالانه (میلیون EUR)
C47: کاتد مس | D47: 8500 | E47: 400000 | F47: =D47*E47/1000000*0.92
C48: اسید سولفوریک | D48: 120 | E48: 1720000 | F48: =D48*E48/1000000*0.92
C49: اسید فسفریک | D49: 650 | E49: 570000 | F49: =D49*E49/1000000*0.92
C50: لجن آندی | D50: 25000 | E50: 1200 | F50: =D50*E50/1000000*0.92
C51: جمع درآمد سالانه | F51: =SUM(F47:F50)
AB55: 3 | AC55: آب | AD55: 9792
C56: جزئیات هزینه های عملیاتی | AB56: 4 | AC56: نیروی کار مستقیم | AD56: 13903806
C57: عنوان | AB57: 5 | AC57: نگهداری | AD57: 17594865
C58: خوراک | D58: 3923478375 | E58: =D48/$D$54*100 | AB58: 6 | AD58: 3849330
C59: یوتیلیتی (هزینه مصرف تاسیسات زیرساختی پشتیبانی تولید) | D59: 68348285 | E59: =D49/$D$54*100 | AB59: مجموع | AD59: 42342591
C60: پرسنلی | D60: 90919737 | E60: =D50/$D$54*100
C61: بازاریابی، فروش و لجستیک | D61: 12363177 | E61: =D51/$D$54*100 | AB61: ردیف | AC61: شرح | AD61: یورو در سال
C62: تعمیر و نگهداری | D62: 164855990 | E62: =D52/$D$54*100 | AB62: 1 | AC62: مواد مصرفی | AD62: 4801267
C63: سایر هزینه ها | D63: 37081385 | E63: =D53/$D$54*100 | AB63: 2 | AC63: برق | AD63: 238506
C64: هزینه های سالانه | D64: 4414042026 | AB64: 3 | AC64: آب | AD64: 162768
C65: درصد هزینه های ارزی | D65: 100 | AB65: 4 | AC65: نیروی کار مستقیم | AD65: 6769915
AB66: 5 | AC66: نگهداری (5 درصد) | AD66: 9022480
C67: مواد اولیه مورد نیاز
C68: ماده اولیه | D68: مقدار سالانه (تن) | E68: قیمت واحد (USD/تن) | F68: هزینه سالانه (میلیون EUR)
C69: کنسانتره مس | D69: 1600000 | E69: 2200 | F69: =D69*E69/1000000*0.92
C70: سنگ فسفات | D70: 1900000 | E70: 85 | F70: =D70*E70/1000000*0.92
C71: مواد شیمیایی و مصرفی | D71: 50000 | E71: 800 | F71: =D71*E71/1000000*0.92
C72: جمع هزینه مواد اولیه | F72: =SUM(F69:F71)
C74: نیازهای یوتیلیتی
C75: یوتیلیتی | D75: مصرف سالانه | E75: واحد | F75: هزینه سالانه (میلیون EUR)
C76: برق | D76: 2500000 | E76: MWh | F76: 15.5
C77: آب | D77: 25000000 | E77: m3 | F77: 12.3
C78: گاز طبیعی | D78: 150000000 | E78: m3 | F78: 28.5
C79: هوای فشرده | D79: 500000000 | E79: Nm3 | F79: 8.2
C80: بخار | D80: 3500000 | E80: ton | F80: 3.8
C81: جمع هزینه یوتیلیتی | F81: =SUM(F76:F80)
C82: جریان نقدی پروژه | AB82: 6 | AC82: هزینه های پیشبینی نشده | AD82: 2314186
C83: نیروی انسانی مورد نیاز
C84: رده شغلی | D84: تعداد | E84: حقوق متوسط سالانه (EUR) | F84: هزینه سالانه (میلیون EUR)
C85: مدیریت ارشد | D85: 25 | E85: 85000 | F85: =D85*E85/1000000
C86: مهندسین | D86: 180 | E86: 55000 | F86: =D86*E86/1000000
C87: تکنسین ها | D87: 320 | E87: 38000 | F87: =D87*E87/1000000
C88: اپراتورها | D88: 580 | E88: 32000 | F88: =D88*E88/1000000
C89: نیروی تعمیرات | D89: 240 | E89: 35000 | F89: =D89*E89/1000000
C90: کارکنان اداری | D90: 155 | E90: 28000 | F90: =D90*E90/1000000
C91: کارکنان پشتیبانی | D91: 200 | E91: 22000 | F91: =D91*E91/1000000
C92: جمع نیروی انسانی | D92: =SUM(D85:D91) | F92: =SUM(F85:F91)
C103: تجهیزات اصلی
C104: تجهیز | D104: تعداد | E104: ظرفیت/مشخصات | F104: هزینه واحد (میلیون EUR) | G104: هزینه کل (میلیون EUR)
C105: کوره ذوب | D105: 4 | E105: 150 تن/ساعت | F105: 45 | G105: =D105*F105
C106: کوره تبدیل | D106: 3 | E106: 120 تن/ساعت | F106: 38 | G106: =D106*F106
C107: کوره آند | D107: 2 | E107: 80 تن/ساعت | F107: 32 | G107: =D107*F107
C108: سلول های الکترولیز | D108: 1200 | E108: 350 آمپر/m2 | F108: 0.25 | G108: =D108*F108
C109: واحد تولید اسید سولفوریک | D109: 2 | E109: 860,000 تن/سال | F109: 85 | G109: =D109*F109
C110: واحد تولید اسید فسفریک | D110: 1 | E110: 570,000 تن/سال | F110: 120 | G110: =D110*F110
C111: تجهیزات خردایش و آسیاب | D111: 1 | E111: 200 تن/ساعت | F111: 65 | G111: =D111*F111
C112: سیستم های حمل مواد | D112: 1 | E112: سیستم کامل | F112: 95 | G112: =D112*F112
C113: جرثقیل ها و تجهیزات بلند کننده | D113: 18 | E113: 50-200 تن | F113: 4.5 | G113: =D113*F113
C114: ترانسفورماتورها و تجهیزات برقی | D114: 1 | E114: 350 MVA | F114: 125 | G114: =D114*F114
C115: سیستم های کنترل و اتوماسیون | D115: 1 | E115: DCS کامل | F115: 78 | G115: =D115*F115
...

Sheet EN
B2: Project Title: | C2: Makran 400,000 ton/year cathode project
B3: Project Sub Title: | C3: Chabahar Smelting and Phosphoric Acid Complex
B5: Project summary
B6: Industry: | C6: Copper and Non-Ferrous Metals
B7: Sub-industry: | C7: Downstream Copper Industry
B8: Location: | C8: Chabahar Free Zone
B9: Project Completion Percentage: | C9: 0
B10: project description | C10: defined with the goal of achieving annual production of 1,000,000 tons of copper cathode for NICICo
B11: Project Execution status | C11: Stopped
B12: Financing status | C12: No action has been taken
B13: Key risks | C13: Financial and feedstock supply limitations
B15: CapEx Breakdown
B16: Category | C16: amount
B17: Total investment | C17: =FA!D17
B18: Engineering & know-how | C18: =FA!D18
B19: equipment | C19: =FA!D19
B20: construction and commissioning | C20: =FA!D20
B21: Utilities | C21: =FA!D21
B22: Pre-operation expenses | C22: =FA!D22
B23: Contingencies | C23: =FA!D23
B24: working capital | C24: =FA!D24
B26: Investment analysis
B27: metric | C27: value
B28: % investment in foreign currency | C28: =FA!D28
B29: construction period (years) | C29: 3
B30: payback period (years) | C30: 20
B31: operating income (EBIT)
B32: Net income
B33: Internal rate of return (IRR) | C33: 0.23
B34: NPV at 10% Discount rate | C34: 2,067 million Euro
B36: Revenue Breakdown
B37: Product | C37: Capacity (Unit of measure)
B38: Copper Cathode | C38: 400,000 ton/year
B39: Sulphuric Acid | C39: 1,720,000 ton/year
B40: Phosphoric Acid | C40: 570,000 ton/year
B41: Anode Slime | C41: 1,200 ton/year
B42: annual Revenue | C42: 5,150 million Euro
B43: % revenue in Foreign currency | C43: 100
B44: Target Market | C44: Export
B46: Expenses breakdown
B47: Category | C47: Euro
B48: Feed | C48: =FA!D48
B49: Utilities | C49: =FA!D49
B50: Personnel | C50: =FA!D50
B51: Marketing, Sales & Logistics | C51: =FA!D51
B52: Maintenance | C52: =FA!D52
B53: Other expanses | C53: =FA!D53
B54: annual expenses | C54: =FA!D54
B55: % expenses in foreign currency | C55: =FA!D55
B57: Cash Flow
C58: Cash Flow
B59: Year 1 | C59: =FA!D58
B60: Year 2 | C60: =FA!D59
B61: Year 3 | C61: =FA!D60
B62: Year 4 | C62: =FA!D61
B63: Year 5 | C63: =FA!D62
B64: Year 6 | C64: =FA!D63
B65: Year 7 | C65: =FA!D64
B66: Year 8 | C66: =FA!D65
B67: Year 9 | C67: =FA!D66
B68: Year 10 | C68: =FA!D67
B70: Project ID
